{"a":"Austinmer","bbox":[150.90898312758483,-34.31172953412011,150.9434524657025,-34.29217778051077],"26_2025_Coastal Inundation":0,"c":"1361","26_2025_Extreme Wind":0,"26_2025_Forest Fire":0.1403,"26_2025_Riverine Flooding":0,"26_2025_Surface Water Flooding":0,"26_2025_Tropical Cyclone Wind":0,"26_2025_Total MVAR":0.1506,"26_2050_Coastal Inundation":0,"26_2050_Extreme Wind":0,"26_2050_Forest Fire":0.1499,"26_2050_Riverine Flooding":0,"26_2050_Surface Water Flooding":0,"26_2050_Tropical Cyclone Wind":0,"26_2050_Total MVAR":0.1572,"26_2100_Coastal Inundation":0,"26_2100_Extreme Wind":0,"26_2100_Forest Fire":0.1499,"26_2100_Riverine Flooding":0,"26_2100_Surface Water Flooding":0,"26_2100_Tropical Cyclone Wind":0,"26_2100_Total MVAR":0.1594,"45_2025_Coastal Inundation":0,"45_2025_Extreme Wind":0,"45_2025_Forest Fire":0.1455,"45_2025_Riverine Flooding":0,"45_2025_Surface Water Flooding":0,"45_2025_Tropical Cyclone Wind":0,"45_2025_Total MVAR":0.1558,"45_2050_Coastal Inundation":0,"45_2050_Extreme Wind":0,"45_2050_Forest Fire":0.1661,"45_2050_Riverine Flooding":0,"45_2050_Surface Water Flooding":0,"45_2050_Tropical Cyclone Wind":0,"45_2050_Total MVAR":0.1793,"45_2100_Coastal Inundation":0,"45_2100_Extreme Wind":0,"45_2100_Forest Fire":0.1763,"45_2100_Riverine Flooding":0,"45_2100_Surface Water Flooding":0,"45_2100_Tropical Cyclone Wind":0,"45_2100_Total MVAR":0.1874,"85_2025_Coastal Inundation":0,"85_2025_Extreme Wind":0,"85_2025_Forest Fire":0.1455,"85_2025_Riverine Flooding":0,"85_2025_Surface Water Flooding":0,"85_2025_Tropical Cyclone Wind":0,"85_2025_Total MVAR":0.1558,"85_2050_Coastal Inundation":0,"85_2050_Extreme Wind":0,"85_2050_Forest Fire":0.1763,"85_2050_Riverine Flooding":0,"85_2050_Surface Water Flooding":0,"85_2050_Tropical Cyclone Wind":0,"85_2050_Total MVAR":0.1874,"85_2100_Coastal Inundation":0,"85_2100_Extreme Wind":0,"85_2100_Forest Fire":0.2248,"85_2100_Riverine Flooding":0,"85_2100_Surface Water Flooding":0,"85_2100_Tropical Cyclone Wind":0,"85_2100_Total MVAR":0.2432}