{"a":"Bamboo Creek","bbox":[145.96522253011779,-17.57008879750494,146.0156947984991,-17.532751766965884],"26_2025_Coastal Inundation":0.0119,"c":"84","26_2025_Extreme Wind":0,"26_2025_Forest Fire":0,"26_2025_Riverine Flooding":0.2143,"26_2025_Surface Water Flooding":0.0119,"26_2025_Tropical Cyclone Wind":0,"26_2025_Total MVAR":0.2262,"26_2050_Coastal Inundation":0.0119,"26_2050_Extreme Wind":0,"26_2050_Forest Fire":0,"26_2050_Riverine Flooding":0.2143,"26_2050_Surface Water Flooding":0.0119,"26_2050_Tropical Cyclone Wind":0,"26_2050_Total MVAR":0.2262,"26_2100_Coastal Inundation":0.0476,"26_2100_Extreme Wind":0,"26_2100_Forest Fire":0,"26_2100_Riverine Flooding":0.2143,"26_2100_Surface Water Flooding":0.0119,"26_2100_Tropical Cyclone Wind":0,"26_2100_Total MVAR":0.2381,"45_2025_Coastal Inundation":0.0119,"45_2025_Extreme Wind":0,"45_2025_Forest Fire":0,"45_2025_Riverine Flooding":0.2143,"45_2025_Surface Water Flooding":0.0119,"45_2025_Tropical Cyclone Wind":0,"45_2025_Total MVAR":0.2262,"45_2050_Coastal Inundation":0.0119,"45_2050_Extreme Wind":0,"45_2050_Forest Fire":0,"45_2050_Riverine Flooding":0.2143,"45_2050_Surface Water Flooding":0.0119,"45_2050_Tropical Cyclone Wind":0,"45_2050_Total MVAR":0.2262,"45_2100_Coastal Inundation":0.0476,"45_2100_Extreme Wind":0,"45_2100_Forest Fire":0,"45_2100_Riverine Flooding":0.2262,"45_2100_Surface Water Flooding":0.0119,"45_2100_Tropical Cyclone Wind":0,"45_2100_Total MVAR":0.2381,"85_2025_Coastal Inundation":0.0119,"85_2025_Extreme Wind":0,"85_2025_Forest Fire":0,"85_2025_Riverine Flooding":0.2143,"85_2025_Surface Water Flooding":0.0119,"85_2025_Tropical Cyclone Wind":0,"85_2025_Total MVAR":0.2262,"85_2050_Coastal Inundation":0.0119,"85_2050_Extreme Wind":0,"85_2050_Forest Fire":0,"85_2050_Riverine Flooding":0.2143,"85_2050_Surface Water Flooding":0.0119,"85_2050_Tropical Cyclone Wind":0,"85_2050_Total MVAR":0.2262,"85_2100_Coastal Inundation":0.0476,"85_2100_Extreme Wind":0,"85_2100_Forest Fire":0,"85_2100_Riverine Flooding":0.2381,"85_2100_Surface Water Flooding":0.0119,"85_2100_Tropical Cyclone Wind":0,"85_2100_Total MVAR":0.2381}