{"a":"Clontarf (Moreton Bay - Qld)","bbox":[153.06841696765056,-27.26337144878816,153.0959753744613,-27.232875548244035],"26_2025_Coastal Inundation":0.0111,"c":"4953","26_2025_Extreme Wind":0,"26_2025_Forest Fire":0,"26_2025_Riverine Flooding":0.0157,"26_2025_Surface Water Flooding":0.0224,"26_2025_Tropical Cyclone Wind":0,"26_2025_Total MVAR":0.0483,"26_2050_Coastal Inundation":0.0131,"26_2050_Extreme Wind":0,"26_2050_Forest Fire":0,"26_2050_Riverine Flooding":0.017,"26_2050_Surface Water Flooding":0.0224,"26_2050_Tropical Cyclone Wind":0,"26_2050_Total MVAR":0.0497,"26_2100_Coastal Inundation":0.0785,"26_2100_Extreme Wind":0,"26_2100_Forest Fire":0,"26_2100_Riverine Flooding":0.0172,"26_2100_Surface Water Flooding":0.0224,"26_2100_Tropical Cyclone Wind":0,"26_2100_Total MVAR":0.0929,"45_2025_Coastal Inundation":0.0111,"45_2025_Extreme Wind":0,"45_2025_Forest Fire":0,"45_2025_Riverine Flooding":0.0164,"45_2025_Surface Water Flooding":0.0224,"45_2025_Tropical Cyclone Wind":0,"45_2025_Total MVAR":0.0483,"45_2050_Coastal Inundation":0.0131,"45_2050_Extreme Wind":0,"45_2050_Forest Fire":0,"45_2050_Riverine Flooding":0.0184,"45_2050_Surface Water Flooding":0.0226,"45_2050_Tropical Cyclone Wind":0,"45_2050_Total MVAR":0.0509,"45_2100_Coastal Inundation":0.0828,"45_2100_Extreme Wind":0,"45_2100_Forest Fire":0,"45_2100_Riverine Flooding":0.019,"45_2100_Surface Water Flooding":0.0226,"45_2100_Tropical Cyclone Wind":0,"45_2100_Total MVAR":0.0977,"85_2025_Coastal Inundation":0.0111,"85_2025_Extreme Wind":0,"85_2025_Forest Fire":0,"85_2025_Riverine Flooding":0.0164,"85_2025_Surface Water Flooding":0.0224,"85_2025_Tropical Cyclone Wind":0,"85_2025_Total MVAR":0.0485,"85_2050_Coastal Inundation":0.0131,"85_2050_Extreme Wind":0,"85_2050_Forest Fire":0,"85_2050_Riverine Flooding":0.0192,"85_2050_Surface Water Flooding":0.0226,"85_2050_Tropical Cyclone Wind":0,"85_2050_Total MVAR":0.0521,"85_2100_Coastal Inundation":0.0832,"85_2100_Extreme Wind":0,"85_2100_Forest Fire":0,"85_2100_Riverine Flooding":0.0226,"85_2100_Surface Water Flooding":0.0234,"85_2100_Tropical Cyclone Wind":0,"85_2100_Total MVAR":0.1014}