{"a":"Concord West","bbox":[151.08142928873443,-33.85626549609025,151.10258637608626,-33.83070203654762],"26_2025_Coastal Inundation":0,"c":"2608","26_2025_Extreme Wind":0,"26_2025_Forest Fire":0,"26_2025_Riverine Flooding":0.0008,"26_2025_Surface Water Flooding":0.0422,"26_2025_Tropical Cyclone Wind":0,"26_2025_Total MVAR":0.0452,"26_2050_Coastal Inundation":0,"26_2050_Extreme Wind":0,"26_2050_Forest Fire":0,"26_2050_Riverine Flooding":0.0008,"26_2050_Surface Water Flooding":0.0422,"26_2050_Tropical Cyclone Wind":0,"26_2050_Total MVAR":0.0452,"26_2100_Coastal Inundation":0.0123,"26_2100_Extreme Wind":0,"26_2100_Forest Fire":0,"26_2100_Riverine Flooding":0.0084,"26_2100_Surface Water Flooding":0.0449,"26_2100_Tropical Cyclone Wind":0,"26_2100_Total MVAR":0.0537,"45_2025_Coastal Inundation":0,"45_2025_Extreme Wind":0,"45_2025_Forest Fire":0,"45_2025_Riverine Flooding":0.0008,"45_2025_Surface Water Flooding":0.0422,"45_2025_Tropical Cyclone Wind":0,"45_2025_Total MVAR":0.0452,"45_2050_Coastal Inundation":0,"45_2050_Extreme Wind":0,"45_2050_Forest Fire":0,"45_2050_Riverine Flooding":0.0008,"45_2050_Surface Water Flooding":0.0422,"45_2050_Tropical Cyclone Wind":0,"45_2050_Total MVAR":0.0452,"45_2100_Coastal Inundation":0.0127,"45_2100_Extreme Wind":0,"45_2100_Forest Fire":0,"45_2100_Riverine Flooding":0.0111,"45_2100_Surface Water Flooding":0.0464,"45_2100_Tropical Cyclone Wind":0,"45_2100_Total MVAR":0.0564,"85_2025_Coastal Inundation":0,"85_2025_Extreme Wind":0,"85_2025_Forest Fire":0,"85_2025_Riverine Flooding":0.0008,"85_2025_Surface Water Flooding":0.0422,"85_2025_Tropical Cyclone Wind":0,"85_2025_Total MVAR":0.0452,"85_2050_Coastal Inundation":0,"85_2050_Extreme Wind":0,"85_2050_Forest Fire":0,"85_2050_Riverine Flooding":0.0008,"85_2050_Surface Water Flooding":0.0422,"85_2050_Tropical Cyclone Wind":0,"85_2050_Total MVAR":0.0456,"85_2100_Coastal Inundation":0.0142,"85_2100_Extreme Wind":0,"85_2100_Forest Fire":0,"85_2100_Riverine Flooding":0.0146,"85_2100_Surface Water Flooding":0.051,"85_2100_Tropical Cyclone Wind":0,"85_2100_Total MVAR":0.0617}