{"a":"Darlington (WA)","bbox":[116.0577065631777,-31.949423004475385,116.1044166586054,-31.899341536336483],"26_2025_Coastal Inundation":0,"c":"1565","26_2025_Extreme Wind":0,"26_2025_Forest Fire":0.5712,"26_2025_Riverine Flooding":0,"26_2025_Surface Water Flooding":0.0013,"26_2025_Tropical Cyclone Wind":0,"26_2025_Total MVAR":0.6204,"26_2050_Coastal Inundation":0,"26_2050_Extreme Wind":0,"26_2050_Forest Fire":0.5712,"26_2050_Riverine Flooding":0,"26_2050_Surface Water Flooding":0.0019,"26_2050_Tropical Cyclone Wind":0,"26_2050_Total MVAR":0.6319,"26_2100_Coastal Inundation":0,"26_2100_Extreme Wind":0,"26_2100_Forest Fire":0.5859,"26_2100_Riverine Flooding":0.0006,"26_2100_Surface Water Flooding":0.0204,"26_2100_Tropical Cyclone Wind":0,"26_2100_Total MVAR":0.6907,"45_2025_Coastal Inundation":0,"45_2025_Extreme Wind":0,"45_2025_Forest Fire":0.5712,"45_2025_Riverine Flooding":0,"45_2025_Surface Water Flooding":0.0013,"45_2025_Tropical Cyclone Wind":0,"45_2025_Total MVAR":0.623,"45_2050_Coastal Inundation":0,"45_2050_Extreme Wind":0,"45_2050_Forest Fire":0.6032,"45_2050_Riverine Flooding":0,"45_2050_Surface Water Flooding":0.0026,"45_2050_Tropical Cyclone Wind":0,"45_2050_Total MVAR":0.701,"45_2100_Coastal Inundation":0,"45_2100_Extreme Wind":0,"45_2100_Forest Fire":0.7201,"45_2100_Riverine Flooding":0.0045,"45_2100_Surface Water Flooding":0.0313,"45_2100_Tropical Cyclone Wind":0,"45_2100_Total MVAR":0.8026,"85_2025_Coastal Inundation":0,"85_2025_Extreme Wind":0,"85_2025_Forest Fire":0.5712,"85_2025_Riverine Flooding":0,"85_2025_Surface Water Flooding":0.0013,"85_2025_Tropical Cyclone Wind":0,"85_2025_Total MVAR":0.6345,"85_2050_Coastal Inundation":0,"85_2050_Extreme Wind":0,"85_2050_Forest Fire":0.6479,"85_2050_Riverine Flooding":0,"85_2050_Surface Water Flooding":0.0026,"85_2050_Tropical Cyclone Wind":0,"85_2050_Total MVAR":0.7131,"85_2100_Coastal Inundation":0,"85_2100_Extreme Wind":0,"85_2100_Forest Fire":0.8677,"85_2100_Riverine Flooding":0.016,"85_2100_Surface Water Flooding":0.0607,"85_2100_Tropical Cyclone Wind":0,"85_2100_Total MVAR":0.9093}