{"a":"Hanwood","bbox":[145.93745608085166,-34.40831616596736,146.12972505780525,-34.30995922004854],"26_2025_Coastal Inundation":0,"c":"760","26_2025_Extreme Wind":0,"26_2025_Forest Fire":0,"26_2025_Riverine Flooding":0.0039,"26_2025_Surface Water Flooding":0,"26_2025_Tropical Cyclone Wind":0,"26_2025_Total MVAR":0.0039,"26_2050_Coastal Inundation":0,"26_2050_Extreme Wind":0,"26_2050_Forest Fire":0,"26_2050_Riverine Flooding":0.0039,"26_2050_Surface Water Flooding":0,"26_2050_Tropical Cyclone Wind":0,"26_2050_Total MVAR":0.0039,"26_2100_Coastal Inundation":0,"26_2100_Extreme Wind":0,"26_2100_Forest Fire":0,"26_2100_Riverine Flooding":0.0039,"26_2100_Surface Water Flooding":0,"26_2100_Tropical Cyclone Wind":0,"26_2100_Total MVAR":0.0039,"45_2025_Coastal Inundation":0,"45_2025_Extreme Wind":0,"45_2025_Forest Fire":0,"45_2025_Riverine Flooding":0.0039,"45_2025_Surface Water Flooding":0,"45_2025_Tropical Cyclone Wind":0,"45_2025_Total MVAR":0.0039,"45_2050_Coastal Inundation":0,"45_2050_Extreme Wind":0,"45_2050_Forest Fire":0,"45_2050_Riverine Flooding":0.0039,"45_2050_Surface Water Flooding":0,"45_2050_Tropical Cyclone Wind":0,"45_2050_Total MVAR":0.0053,"45_2100_Coastal Inundation":0,"45_2100_Extreme Wind":0,"45_2100_Forest Fire":0.0013,"45_2100_Riverine Flooding":0.0039,"45_2100_Surface Water Flooding":0,"45_2100_Tropical Cyclone Wind":0,"45_2100_Total MVAR":0.0079,"85_2025_Coastal Inundation":0,"85_2025_Extreme Wind":0,"85_2025_Forest Fire":0,"85_2025_Riverine Flooding":0.0039,"85_2025_Surface Water Flooding":0,"85_2025_Tropical Cyclone Wind":0,"85_2025_Total MVAR":0.0039,"85_2050_Coastal Inundation":0,"85_2050_Extreme Wind":0,"85_2050_Forest Fire":0.0013,"85_2050_Riverine Flooding":0.0039,"85_2050_Surface Water Flooding":0,"85_2050_Tropical Cyclone Wind":0,"85_2050_Total MVAR":0.0079,"85_2100_Coastal Inundation":0,"85_2100_Extreme Wind":0,"85_2100_Forest Fire":0.0039,"85_2100_Riverine Flooding":0.0039,"85_2100_Surface Water Flooding":0,"85_2100_Tropical Cyclone Wind":0,"85_2100_Total MVAR":0.0118}