{"a":"Indented Head","bbox":[144.68982352970488,-38.15021051532049,144.72022090973041,-38.12025686489506],"26_2025_Coastal Inundation":0.0006,"c":"1775","26_2025_Extreme Wind":0,"26_2025_Forest Fire":0,"26_2025_Riverine Flooding":0.0011,"26_2025_Surface Water Flooding":0.0011,"26_2025_Tropical Cyclone Wind":0,"26_2025_Total MVAR":0.0039,"26_2050_Coastal Inundation":0.0006,"26_2050_Extreme Wind":0,"26_2050_Forest Fire":0,"26_2050_Riverine Flooding":0.0011,"26_2050_Surface Water Flooding":0.0023,"26_2050_Tropical Cyclone Wind":0,"26_2050_Total MVAR":0.0079,"26_2100_Coastal Inundation":0.1566,"26_2100_Extreme Wind":0,"26_2100_Forest Fire":0,"26_2100_Riverine Flooding":0.0023,"26_2100_Surface Water Flooding":0.0062,"26_2100_Tropical Cyclone Wind":0,"26_2100_Total MVAR":0.1628,"45_2025_Coastal Inundation":0.0006,"45_2025_Extreme Wind":0,"45_2025_Forest Fire":0,"45_2025_Riverine Flooding":0.0011,"45_2025_Surface Water Flooding":0.0011,"45_2025_Tropical Cyclone Wind":0,"45_2025_Total MVAR":0.0039,"45_2050_Coastal Inundation":0.0006,"45_2050_Extreme Wind":0,"45_2050_Forest Fire":0,"45_2050_Riverine Flooding":0.0011,"45_2050_Surface Water Flooding":0.0062,"45_2050_Tropical Cyclone Wind":0,"45_2050_Total MVAR":0.009,"45_2100_Coastal Inundation":0.1696,"45_2100_Extreme Wind":0,"45_2100_Forest Fire":0,"45_2100_Riverine Flooding":0.0023,"45_2100_Surface Water Flooding":0.0062,"45_2100_Tropical Cyclone Wind":0,"45_2100_Total MVAR":0.1741,"85_2025_Coastal Inundation":0.0006,"85_2025_Extreme Wind":0,"85_2025_Forest Fire":0,"85_2025_Riverine Flooding":0.0011,"85_2025_Surface Water Flooding":0.0011,"85_2025_Tropical Cyclone Wind":0,"85_2025_Total MVAR":0.0039,"85_2050_Coastal Inundation":0.0006,"85_2050_Extreme Wind":0,"85_2050_Forest Fire":0,"85_2050_Riverine Flooding":0.0023,"85_2050_Surface Water Flooding":0.0062,"85_2050_Tropical Cyclone Wind":0,"85_2050_Total MVAR":0.009,"85_2100_Coastal Inundation":0.1746,"85_2100_Extreme Wind":0,"85_2100_Forest Fire":0,"85_2100_Riverine Flooding":0.0023,"85_2100_Surface Water Flooding":0.0068,"85_2100_Tropical Cyclone Wind":0,"85_2100_Total MVAR":0.182}