{"a":"Kewdale","bbox":[115.91970965385468,-31.997841490535453,115.98530670002734,-31.963124345585225],"26_2025_Coastal Inundation":0,"c":"4345","26_2025_Extreme Wind":0,"26_2025_Forest Fire":0,"26_2025_Riverine Flooding":0,"26_2025_Surface Water Flooding":0.0039,"26_2025_Tropical Cyclone Wind":0,"26_2025_Total MVAR":0.0039,"26_2050_Coastal Inundation":0,"26_2050_Extreme Wind":0,"26_2050_Forest Fire":0,"26_2050_Riverine Flooding":0,"26_2050_Surface Water Flooding":0.0048,"26_2050_Tropical Cyclone Wind":0,"26_2050_Total MVAR":0.0048,"26_2100_Coastal Inundation":0,"26_2100_Extreme Wind":0,"26_2100_Forest Fire":0,"26_2100_Riverine Flooding":0,"26_2100_Surface Water Flooding":0.0242,"26_2100_Tropical Cyclone Wind":0,"26_2100_Total MVAR":0.0276,"45_2025_Coastal Inundation":0,"45_2025_Extreme Wind":0,"45_2025_Forest Fire":0,"45_2025_Riverine Flooding":0,"45_2025_Surface Water Flooding":0.0039,"45_2025_Tropical Cyclone Wind":0,"45_2025_Total MVAR":0.0044,"45_2050_Coastal Inundation":0,"45_2050_Extreme Wind":0,"45_2050_Forest Fire":0,"45_2050_Riverine Flooding":0,"45_2050_Surface Water Flooding":0.0064,"45_2050_Tropical Cyclone Wind":0,"45_2050_Total MVAR":0.0074,"45_2100_Coastal Inundation":0,"45_2100_Extreme Wind":0,"45_2100_Forest Fire":0,"45_2100_Riverine Flooding":0,"45_2100_Surface Water Flooding":0.0525,"45_2100_Tropical Cyclone Wind":0,"45_2100_Total MVAR":0.0663,"85_2025_Coastal Inundation":0,"85_2025_Extreme Wind":0,"85_2025_Forest Fire":0,"85_2025_Riverine Flooding":0,"85_2025_Surface Water Flooding":0.0039,"85_2025_Tropical Cyclone Wind":0,"85_2025_Total MVAR":0.0044,"85_2050_Coastal Inundation":0,"85_2050_Extreme Wind":0,"85_2050_Forest Fire":0,"85_2050_Riverine Flooding":0,"85_2050_Surface Water Flooding":0.0074,"85_2050_Tropical Cyclone Wind":0,"85_2050_Total MVAR":0.0094,"85_2100_Coastal Inundation":0,"85_2100_Extreme Wind":0,"85_2100_Forest Fire":0,"85_2100_Riverine Flooding":0.0014,"85_2100_Surface Water Flooding":0.1158,"85_2100_Tropical Cyclone Wind":0,"85_2100_Total MVAR":0.1298}