{"a":"Killingworth (NSW)","bbox":[151.51381756200064,-32.960319674719365,151.58129256251598,-32.89673177184185],"26_2025_Coastal Inundation":0,"c":"368","26_2025_Extreme Wind":0,"26_2025_Forest Fire":0.3152,"26_2025_Riverine Flooding":0,"26_2025_Surface Water Flooding":0,"26_2025_Tropical Cyclone Wind":0,"26_2025_Total MVAR":0.3234,"26_2050_Coastal Inundation":0,"26_2050_Extreme Wind":0,"26_2050_Forest Fire":0.3234,"26_2050_Riverine Flooding":0,"26_2050_Surface Water Flooding":0,"26_2050_Tropical Cyclone Wind":0,"26_2050_Total MVAR":0.3533,"26_2100_Coastal Inundation":0,"26_2100_Extreme Wind":0,"26_2100_Forest Fire":0.337,"26_2100_Riverine Flooding":0,"26_2100_Surface Water Flooding":0,"26_2100_Tropical Cyclone Wind":0,"26_2100_Total MVAR":0.3533,"45_2025_Coastal Inundation":0,"45_2025_Extreme Wind":0,"45_2025_Forest Fire":0.3152,"45_2025_Riverine Flooding":0,"45_2025_Surface Water Flooding":0,"45_2025_Tropical Cyclone Wind":0,"45_2025_Total MVAR":0.337,"45_2050_Coastal Inundation":0,"45_2050_Extreme Wind":0,"45_2050_Forest Fire":0.3641,"45_2050_Riverine Flooding":0,"45_2050_Surface Water Flooding":0,"45_2050_Tropical Cyclone Wind":0,"45_2050_Total MVAR":0.3804,"45_2100_Coastal Inundation":0,"45_2100_Extreme Wind":0,"45_2100_Forest Fire":0.3641,"45_2100_Riverine Flooding":0,"45_2100_Surface Water Flooding":0,"45_2100_Tropical Cyclone Wind":0,"45_2100_Total MVAR":0.3832,"85_2025_Coastal Inundation":0,"85_2025_Extreme Wind":0,"85_2025_Forest Fire":0.3234,"85_2025_Riverine Flooding":0,"85_2025_Surface Water Flooding":0,"85_2025_Tropical Cyclone Wind":0,"85_2025_Total MVAR":0.337,"85_2050_Coastal Inundation":0,"85_2050_Extreme Wind":0,"85_2050_Forest Fire":0.3804,"85_2050_Riverine Flooding":0,"85_2050_Surface Water Flooding":0,"85_2050_Tropical Cyclone Wind":0,"85_2050_Total MVAR":0.3995,"85_2100_Coastal Inundation":0,"85_2100_Extreme Wind":0,"85_2100_Forest Fire":0.4402,"85_2100_Riverine Flooding":0,"85_2100_Surface Water Flooding":0,"85_2100_Tropical Cyclone Wind":0,"85_2100_Total MVAR":0.4755}