{"a":"Mount Mort","bbox":[152.38279235169657,-27.865456367982542,152.49267504923483,-27.70572638726509],"26_2025_Coastal Inundation":0,"c":"161","26_2025_Extreme Wind":0,"26_2025_Forest Fire":0,"26_2025_Riverine Flooding":0.0559,"26_2025_Surface Water Flooding":0.0062,"26_2025_Tropical Cyclone Wind":0,"26_2025_Total MVAR":0.0559,"26_2050_Coastal Inundation":0,"26_2050_Extreme Wind":0,"26_2050_Forest Fire":0,"26_2050_Riverine Flooding":0.0559,"26_2050_Surface Water Flooding":0.0062,"26_2050_Tropical Cyclone Wind":0,"26_2050_Total MVAR":0.0559,"26_2100_Coastal Inundation":0,"26_2100_Extreme Wind":0,"26_2100_Forest Fire":0,"26_2100_Riverine Flooding":0.0559,"26_2100_Surface Water Flooding":0.0062,"26_2100_Tropical Cyclone Wind":0,"26_2100_Total MVAR":0.0559,"45_2025_Coastal Inundation":0,"45_2025_Extreme Wind":0,"45_2025_Forest Fire":0,"45_2025_Riverine Flooding":0.0559,"45_2025_Surface Water Flooding":0.0062,"45_2025_Tropical Cyclone Wind":0,"45_2025_Total MVAR":0.0559,"45_2050_Coastal Inundation":0,"45_2050_Extreme Wind":0,"45_2050_Forest Fire":0,"45_2050_Riverine Flooding":0.0559,"45_2050_Surface Water Flooding":0.0062,"45_2050_Tropical Cyclone Wind":0,"45_2050_Total MVAR":0.0559,"45_2100_Coastal Inundation":0,"45_2100_Extreme Wind":0,"45_2100_Forest Fire":0,"45_2100_Riverine Flooding":0.0559,"45_2100_Surface Water Flooding":0.0062,"45_2100_Tropical Cyclone Wind":0,"45_2100_Total MVAR":0.0559,"85_2025_Coastal Inundation":0,"85_2025_Extreme Wind":0,"85_2025_Forest Fire":0,"85_2025_Riverine Flooding":0.0559,"85_2025_Surface Water Flooding":0.0062,"85_2025_Tropical Cyclone Wind":0,"85_2025_Total MVAR":0.0559,"85_2050_Coastal Inundation":0,"85_2050_Extreme Wind":0,"85_2050_Forest Fire":0,"85_2050_Riverine Flooding":0.0559,"85_2050_Surface Water Flooding":0.0062,"85_2050_Tropical Cyclone Wind":0,"85_2050_Total MVAR":0.0559,"85_2100_Coastal Inundation":0,"85_2100_Extreme Wind":0,"85_2100_Forest Fire":0,"85_2100_Riverine Flooding":0.0621,"85_2100_Surface Water Flooding":0.0062,"85_2100_Tropical Cyclone Wind":0,"85_2100_Total MVAR":0.0683}