{"a":"Parkerville","bbox":[116.10395716300842,-31.900647798836328,116.1622701339819,-31.83844388962015],"26_2025_Coastal Inundation":0,"c":"1058","26_2025_Extreme Wind":0,"26_2025_Forest Fire":0.6219,"26_2025_Riverine Flooding":0.0265,"26_2025_Surface Water Flooding":0.0038,"26_2025_Tropical Cyclone Wind":0,"26_2025_Total MVAR":0.6607,"26_2050_Coastal Inundation":0,"26_2050_Extreme Wind":0,"26_2050_Forest Fire":0.6219,"26_2050_Riverine Flooding":0.0284,"26_2050_Surface Water Flooding":0.0038,"26_2050_Tropical Cyclone Wind":0,"26_2050_Total MVAR":0.6607,"26_2100_Coastal Inundation":0,"26_2100_Extreme Wind":0,"26_2100_Forest Fire":0.6219,"26_2100_Riverine Flooding":0.0378,"26_2100_Surface Water Flooding":0.0132,"26_2100_Tropical Cyclone Wind":0,"26_2100_Total MVAR":0.673,"45_2025_Coastal Inundation":0,"45_2025_Extreme Wind":0,"45_2025_Forest Fire":0.6219,"45_2025_Riverine Flooding":0.0265,"45_2025_Surface Water Flooding":0.0038,"45_2025_Tropical Cyclone Wind":0,"45_2025_Total MVAR":0.6635,"45_2050_Coastal Inundation":0,"45_2050_Extreme Wind":0,"45_2050_Forest Fire":0.6512,"45_2050_Riverine Flooding":0.0284,"45_2050_Surface Water Flooding":0.0038,"45_2050_Tropical Cyclone Wind":0,"45_2050_Total MVAR":0.7004,"45_2100_Coastal Inundation":0,"45_2100_Extreme Wind":0,"45_2100_Forest Fire":0.725,"45_2100_Riverine Flooding":0.0444,"45_2100_Surface Water Flooding":0.018,"45_2100_Tropical Cyclone Wind":0,"45_2100_Total MVAR":0.8062,"85_2025_Coastal Inundation":0,"85_2025_Extreme Wind":0,"85_2025_Forest Fire":0.6219,"85_2025_Riverine Flooding":0.0265,"85_2025_Surface Water Flooding":0.0038,"85_2025_Tropical Cyclone Wind":0,"85_2025_Total MVAR":0.6975,"85_2050_Coastal Inundation":0,"85_2050_Extreme Wind":0,"85_2050_Forest Fire":0.69,"85_2050_Riverine Flooding":0.0293,"85_2050_Surface Water Flooding":0.0057,"85_2050_Tropical Cyclone Wind":0,"85_2050_Total MVAR":0.7353,"85_2100_Coastal Inundation":0,"85_2100_Extreme Wind":0,"85_2100_Forest Fire":0.8611,"85_2100_Riverine Flooding":0.0501,"85_2100_Surface Water Flooding":0.0284,"85_2100_Tropical Cyclone Wind":0,"85_2100_Total MVAR":0.9225}