{"a":"South Wharf","bbox":[144.9468789320517,-37.827590840435676,144.9569770324723,-37.823040080536416],"26_2025_Coastal Inundation":0.0205,"c":"292","26_2025_Extreme Wind":0,"26_2025_Forest Fire":0,"26_2025_Riverine Flooding":0,"26_2025_Surface Water Flooding":0,"26_2025_Tropical Cyclone Wind":0,"26_2025_Total MVAR":0.024,"26_2050_Coastal Inundation":0.089,"26_2050_Extreme Wind":0,"26_2050_Forest Fire":0,"26_2050_Riverine Flooding":0,"26_2050_Surface Water Flooding":0,"26_2050_Tropical Cyclone Wind":0,"26_2050_Total MVAR":0.0993,"26_2100_Coastal Inundation":0.9384,"26_2100_Extreme Wind":0,"26_2100_Forest Fire":0,"26_2100_Riverine Flooding":0,"26_2100_Surface Water Flooding":0,"26_2100_Tropical Cyclone Wind":0,"26_2100_Total MVAR":0.9418,"45_2025_Coastal Inundation":0.0205,"45_2025_Extreme Wind":0,"45_2025_Forest Fire":0,"45_2025_Riverine Flooding":0,"45_2025_Surface Water Flooding":0,"45_2025_Tropical Cyclone Wind":0,"45_2025_Total MVAR":0.024,"45_2050_Coastal Inundation":0.0959,"45_2050_Extreme Wind":0,"45_2050_Forest Fire":0,"45_2050_Riverine Flooding":0,"45_2050_Surface Water Flooding":0,"45_2050_Tropical Cyclone Wind":0,"45_2050_Total MVAR":0.0993,"45_2100_Coastal Inundation":0.9384,"45_2100_Extreme Wind":0,"45_2100_Forest Fire":0,"45_2100_Riverine Flooding":0,"45_2100_Surface Water Flooding":0,"45_2100_Tropical Cyclone Wind":0,"45_2100_Total MVAR":0.9555,"85_2025_Coastal Inundation":0.0205,"85_2025_Extreme Wind":0,"85_2025_Forest Fire":0,"85_2025_Riverine Flooding":0,"85_2025_Surface Water Flooding":0,"85_2025_Tropical Cyclone Wind":0,"85_2025_Total MVAR":0.024,"85_2050_Coastal Inundation":0.0959,"85_2050_Extreme Wind":0,"85_2050_Forest Fire":0,"85_2050_Riverine Flooding":0,"85_2050_Surface Water Flooding":0,"85_2050_Tropical Cyclone Wind":0,"85_2050_Total MVAR":0.0993,"85_2100_Coastal Inundation":0.9384,"85_2100_Extreme Wind":0,"85_2100_Forest Fire":0,"85_2100_Riverine Flooding":0,"85_2100_Surface Water Flooding":0,"85_2100_Tropical Cyclone Wind":0,"85_2100_Total MVAR":0.9555}