{"a":"Swan Reach (SA)","bbox":[139.43809693834686,-34.660510449143764,139.75888767984026,-34.47643004129025],"26_2025_Coastal Inundation":0.0046,"c":"433","26_2025_Extreme Wind":0,"26_2025_Forest Fire":0,"26_2025_Riverine Flooding":0.1409,"26_2025_Surface Water Flooding":0.0139,"26_2025_Tropical Cyclone Wind":0,"26_2025_Total MVAR":0.1524,"26_2050_Coastal Inundation":0.0046,"26_2050_Extreme Wind":0,"26_2050_Forest Fire":0,"26_2050_Riverine Flooding":0.1409,"26_2050_Surface Water Flooding":0.0139,"26_2050_Tropical Cyclone Wind":0,"26_2050_Total MVAR":0.1524,"26_2100_Coastal Inundation":0.0046,"26_2100_Extreme Wind":0,"26_2100_Forest Fire":0,"26_2100_Riverine Flooding":0.1409,"26_2100_Surface Water Flooding":0.0139,"26_2100_Tropical Cyclone Wind":0,"26_2100_Total MVAR":0.1524,"45_2025_Coastal Inundation":0.0046,"45_2025_Extreme Wind":0,"45_2025_Forest Fire":0,"45_2025_Riverine Flooding":0.1409,"45_2025_Surface Water Flooding":0.0139,"45_2025_Tropical Cyclone Wind":0,"45_2025_Total MVAR":0.1524,"45_2050_Coastal Inundation":0.0046,"45_2050_Extreme Wind":0,"45_2050_Forest Fire":0,"45_2050_Riverine Flooding":0.1409,"45_2050_Surface Water Flooding":0.0139,"45_2050_Tropical Cyclone Wind":0,"45_2050_Total MVAR":0.1524,"45_2100_Coastal Inundation":0.0046,"45_2100_Extreme Wind":0,"45_2100_Forest Fire":0,"45_2100_Riverine Flooding":0.1409,"45_2100_Surface Water Flooding":0.0139,"45_2100_Tropical Cyclone Wind":0,"45_2100_Total MVAR":0.1524,"85_2025_Coastal Inundation":0.0046,"85_2025_Extreme Wind":0,"85_2025_Forest Fire":0,"85_2025_Riverine Flooding":0.1409,"85_2025_Surface Water Flooding":0.0139,"85_2025_Tropical Cyclone Wind":0,"85_2025_Total MVAR":0.1524,"85_2050_Coastal Inundation":0.0046,"85_2050_Extreme Wind":0,"85_2050_Forest Fire":0,"85_2050_Riverine Flooding":0.1409,"85_2050_Surface Water Flooding":0.0139,"85_2050_Tropical Cyclone Wind":0,"85_2050_Total MVAR":0.1524,"85_2100_Coastal Inundation":0.0046,"85_2100_Extreme Wind":0,"85_2100_Forest Fire":0,"85_2100_Riverine Flooding":0.1409,"85_2100_Surface Water Flooding":0.0139,"85_2100_Tropical Cyclone Wind":0,"85_2100_Total MVAR":0.1524}