{"a":"Woodlands (Qld)","bbox":[152.2559890903133,-27.632314372856047,152.3125410953411,-27.590114370425084],"26_2025_Coastal Inundation":0,"c":"70","26_2025_Extreme Wind":0,"26_2025_Forest Fire":0,"26_2025_Riverine Flooding":0.1143,"26_2025_Surface Water Flooding":0.0429,"26_2025_Tropical Cyclone Wind":0,"26_2025_Total MVAR":0.1571,"26_2050_Coastal Inundation":0,"26_2050_Extreme Wind":0,"26_2050_Forest Fire":0,"26_2050_Riverine Flooding":0.1143,"26_2050_Surface Water Flooding":0.0429,"26_2050_Tropical Cyclone Wind":0,"26_2050_Total MVAR":0.1571,"26_2100_Coastal Inundation":0,"26_2100_Extreme Wind":0,"26_2100_Forest Fire":0,"26_2100_Riverine Flooding":0.1143,"26_2100_Surface Water Flooding":0.0429,"26_2100_Tropical Cyclone Wind":0,"26_2100_Total MVAR":0.1571,"45_2025_Coastal Inundation":0,"45_2025_Extreme Wind":0,"45_2025_Forest Fire":0,"45_2025_Riverine Flooding":0.1143,"45_2025_Surface Water Flooding":0.0429,"45_2025_Tropical Cyclone Wind":0,"45_2025_Total MVAR":0.1571,"45_2050_Coastal Inundation":0,"45_2050_Extreme Wind":0,"45_2050_Forest Fire":0,"45_2050_Riverine Flooding":0.1143,"45_2050_Surface Water Flooding":0.0429,"45_2050_Tropical Cyclone Wind":0,"45_2050_Total MVAR":0.1571,"45_2100_Coastal Inundation":0,"45_2100_Extreme Wind":0,"45_2100_Forest Fire":0,"45_2100_Riverine Flooding":0.1143,"45_2100_Surface Water Flooding":0.0429,"45_2100_Tropical Cyclone Wind":0,"45_2100_Total MVAR":0.1571,"85_2025_Coastal Inundation":0,"85_2025_Extreme Wind":0,"85_2025_Forest Fire":0,"85_2025_Riverine Flooding":0.1143,"85_2025_Surface Water Flooding":0.0429,"85_2025_Tropical Cyclone Wind":0,"85_2025_Total MVAR":0.1571,"85_2050_Coastal Inundation":0,"85_2050_Extreme Wind":0,"85_2050_Forest Fire":0,"85_2050_Riverine Flooding":0.1143,"85_2050_Surface Water Flooding":0.0429,"85_2050_Tropical Cyclone Wind":0,"85_2050_Total MVAR":0.1571,"85_2100_Coastal Inundation":0,"85_2100_Extreme Wind":0,"85_2100_Forest Fire":0,"85_2100_Riverine Flooding":0.1143,"85_2100_Surface Water Flooding":0.0429,"85_2100_Tropical Cyclone Wind":0,"85_2100_Total MVAR":0.1571}